rvc_dv_clone/__init__.py
rvc_dv_clone/config.py
rvc_dv_clone/misc.py
rvc_dv_clone/rvc_infer.py
rvc_dv_clone/vc_infer_pipeline.py
rvc_dv_clone/configs/32k.json
rvc_dv_clone/configs/40k.json
rvc_dv_clone/configs/48k.json
rvc_dv_clone/infer_pack/__init__.py
rvc_dv_clone/infer_pack/attentions.py
rvc_dv_clone/infer_pack/audio.py
rvc_dv_clone/infer_pack/commons.py
rvc_dv_clone/infer_pack/models.py
rvc_dv_clone/infer_pack/modules.py
rvc_dv_clone/infer_pack/transforms.py
rvc_dv_clone/lib/__init__.py
rvc_dv_clone/lib/rmvpe.py
rvc_dv_clone/lib/slicer2.py
rvc_dv_clone/lib/infer_pack/__init__.py
rvc_dv_clone/lib/infer_pack/attentions.py
rvc_dv_clone/lib/infer_pack/commons.py
rvc_dv_clone/lib/infer_pack/models.py
rvc_dv_clone/lib/infer_pack/models_dml.py
rvc_dv_clone/lib/infer_pack/models_onnx.py
rvc_dv_clone/lib/infer_pack/modules.py
rvc_dv_clone/lib/infer_pack/onnx_inference.py
rvc_dv_clone/lib/infer_pack/transforms.py
rvc_dv_clone/lib/uvr5_pack/__init__.py
rvc_dv_clone/lib/uvr5_pack/utils.py
rvc_dv_clone/lib/uvr5_pack/lib_v5/__init__.py
rvc_dv_clone/lib/uvr5_pack/lib_v5/dataset.py
rvc_dv_clone/lib/uvr5_pack/lib_v5/layers.py
rvc_dv_clone/lib/uvr5_pack/lib_v5/layers_123812KB .py
rvc_dv_clone/lib/uvr5_pack/lib_v5/layers_123821KB.py
rvc_dv_clone/lib/uvr5_pack/lib_v5/layers_33966KB.py
rvc_dv_clone/lib/uvr5_pack/lib_v5/layers_537227KB.py
rvc_dv_clone/lib/uvr5_pack/lib_v5/layers_537238KB.py
rvc_dv_clone/lib/uvr5_pack/lib_v5/layers_new.py
rvc_dv_clone/lib/uvr5_pack/lib_v5/model_param_init.py
rvc_dv_clone/lib/uvr5_pack/lib_v5/nets.py
rvc_dv_clone/lib/uvr5_pack/lib_v5/nets_123812KB.py
rvc_dv_clone/lib/uvr5_pack/lib_v5/nets_123821KB.py
rvc_dv_clone/lib/uvr5_pack/lib_v5/nets_33966KB.py
rvc_dv_clone/lib/uvr5_pack/lib_v5/nets_537227KB.py
rvc_dv_clone/lib/uvr5_pack/lib_v5/nets_537238KB.py
rvc_dv_clone/lib/uvr5_pack/lib_v5/nets_61968KB.py
rvc_dv_clone/lib/uvr5_pack/lib_v5/nets_new.py
rvc_dv_clone/lib/uvr5_pack/lib_v5/spec_utils.py
rvc_dv_clone/lib/uvr5_pack/lib_v5/modelparams/__init__.py
rvc_dv_clone-0.4.0.dist-info/LICENSE
rvc_dv_clone-0.4.0.dist-info/METADATA
rvc_dv_clone-0.4.0.dist-info/WHEEL
rvc_dv_clone-0.4.0.dist-info/top_level.txt
rvc_dv_clone-0.4.0.dist-info/RECORD
