Metadata-Version: 2.1
Name: rvc-dv-clone
Version: 0.4.0
Summary: Retrieval-based Voice Conversion library
Author: Alakxender
Author-email: alakxender@gmail.com
Requires-Python: >=3.8
License-File: LICENSE
Requires-Dist: torch>=2.0.0
Requires-Dist: torchaudio>=2.0.0
Requires-Dist: numpy
Requires-Dist: scipy
Requires-Dist: librosa
Requires-Dist: fairseq
Requires-Dist: ffmpeg-python
Requires-Dist: soundfile
Requires-Dist: pyworld
Requires-Dist: faiss-cpu
Requires-Dist: torchcrepe
Requires-Dist: pyyaml
Requires-Dist: praat-parselmouth
